datacube_ows/__init__.py
datacube_ows/_version.py
datacube_ows/band_utils.py
datacube_ows/cfg_parser_impl.py
datacube_ows/config_toolkit.py
datacube_ows/config_utils.py
datacube_ows/data.py
datacube_ows/feature_info.py
datacube_ows/gunicorn_config.py
datacube_ows/http_utils.py
datacube_ows/legend_generator.py
datacube_ows/legend_utils.py
datacube_ows/loading.py
datacube_ows/ogc.py
datacube_ows/ogc_exceptions.py
datacube_ows/ogc_utils.py
datacube_ows/ows_cfg_example.py
datacube_ows/ows_configuration.py
datacube_ows/protocol_versions.py
datacube_ows/query_profiler.py
datacube_ows/resource_limits.py
datacube_ows/tile_matrix_sets.py
datacube_ows/time_utils.py
datacube_ows/update_ranges_impl.py
datacube_ows/utils.py
datacube_ows/wcs1.py
datacube_ows/wcs1_utils.py
datacube_ows/wcs2.py
datacube_ows/wcs2_utils.py
datacube_ows/wcs_scaler.py
datacube_ows/wcs_utils.py
datacube_ows/wms.py
datacube_ows/wms_utils.py
datacube_ows/wmts.py
datacube_ows/wsgi.py
datacube_ows/index/__init__.py
datacube_ows/index/api.py
datacube_ows/index/driver.py
datacube_ows/index/sql.py
datacube_ows/index/postgis/__init__.py
datacube_ows/index/postgis/api.py
datacube_ows/index/postgis/product_ranges.py
datacube_ows/index/postgres/__init__.py
datacube_ows/index/postgres/api.py
datacube_ows/index/postgres/mv_index.py
datacube_ows/index/postgres/product_ranges.py
datacube_ows/sql/postgis/ows_schema/bootstrap/001_create_schema_isolated.sql
datacube_ows/sql/postgis/ows_schema/bootstrap/002_schema_perms_isolated.sql
datacube_ows/sql/postgis/ows_schema/bootstrap/010_layer_range_owner_isolated.sql
datacube_ows/sql/postgis/ows_schema/create/001_switch_to_admin_user.sql
datacube_ows/sql/postgis/ows_schema/create/002_create_layer_rng.sql
datacube_ows/sql/postgis/ows_schema/grants/001_grant_usage.sql
datacube_ows/sql/postgis/ows_schema/grants/002_grant_range_read.sql
datacube_ows/sql/postgis/ows_schema/grants/010_grant_writetables.sql
datacube_ows/sql/postgres/extent_views/create/001_switch_to_manage_user.sql
datacube_ows-1.9.8.dist-info/licenses/LICENSE
datacube_ows-1.9.8.dist-info/METADATA
datacube_ows-1.9.8.dist-info/WHEEL
datacube_ows-1.9.8.dist-info/entry_points.txt
datacube_ows-1.9.8.dist-info/top_level.txt
datacube_ows-1.9.8.dist-info/RECORD
