Metadata-Version: 2.4
Name: datacube_ows
Version: 1.9.8
Summary: Open Data Cube Open Web Services
Author-email: Open Data Cube <earth.observation@ga.gov.au>
License-Expression: Apache-2.0
Project-URL: Homepage, https://github.com/opendatacube/datacube-ows
Keywords: datacube,wms,wcs
Classifier: Development Status :: 2 - Pre-Alpha
Classifier: Intended Audience :: Developers
Classifier: Natural Language :: English
Classifier: Programming Language :: Python
Classifier: Programming Language :: Python :: 3
Classifier: Programming Language :: Python :: 3.11
Classifier: Programming Language :: Python :: 3.12
Classifier: Programming Language :: Python :: 3.13
Requires-Python: >=3.11.0
License-File: LICENSE
Requires-Dist: Babel
Requires-Dist: Flask-Babel>3.0.0
Requires-Dist: Pillow>=10.2.0
Requires-Dist: affine
Requires-Dist: antimeridian
Requires-Dist: click
Requires-Dist: datacube[performance,s3]<1.10.0,>=1.9.13
Requires-Dist: deepdiff
Requires-Dist: flask
Requires-Dist: fsspec
Requires-Dist: geoalchemy2
Requires-Dist: importlib_metadata
Requires-Dist: lark
Requires-Dist: matplotlib
Requires-Dist: numpy>=1.22
Requires-Dist: prometheus_flask_exporter
Requires-Dist: pyows
Requires-Dist: pyparsing
Requires-Dist: python_dateutil
Requires-Dist: python_slugify
Requires-Dist: rasterio
Requires-Dist: regex
Requires-Dist: requests
Requires-Dist: scipy
Requires-Dist: timezonefinder!=6.6.0
Requires-Dist: urllib3
Requires-Dist: xarray
Provides-Extra: dev
Requires-Dist: mypy; extra == "dev"
Requires-Dist: pydevd-pycharm~=252.26830.99; extra == "dev"
Requires-Dist: pylint; extra == "dev"
Requires-Dist: ruff; extra == "dev"
Requires-Dist: ty; extra == "dev"
Requires-Dist: types-python-dateutil; extra == "dev"
Requires-Dist: types-PyYAML; extra == "dev"
Requires-Dist: types-requests; extra == "dev"
Provides-Extra: ops
Requires-Dist: blinker; extra == "ops"
Requires-Dist: gevent; extra == "ops"
Requires-Dist: gunicorn>=22.0.0; extra == "ops"
Requires-Dist: gunicorn[gevent]; extra == "ops"
Requires-Dist: prometheus_client; extra == "ops"
Requires-Dist: psycopg2; extra == "ops"
Requires-Dist: psycopg[c]; extra == "ops"
Requires-Dist: sentry_sdk; extra == "ops"
Provides-Extra: postgres
Requires-Dist: psycopg2; extra == "postgres"
Provides-Extra: setup
Requires-Dist: setuptools; extra == "setup"
Requires-Dist: setuptools_scm; extra == "setup"
Provides-Extra: test
Requires-Dist: flask-cors; extra == "test"
Requires-Dist: fsspec; extra == "test"
Requires-Dist: lxml; extra == "test"
Requires-Dist: owslib>0.29.2; extra == "test"
Requires-Dist: psycopg2; extra == "test"
Requires-Dist: pytest; extra == "test"
Requires-Dist: pytest_cov; extra == "test"
Requires-Dist: pytest_localserver; extra == "test"
Requires-Dist: pytest_mock; extra == "test"
Provides-Extra: all
Requires-Dist: datacube_ows[dev,ops,test]; extra == "all"
Dynamic: license-file
